task3/f1_fsm.sv
module f1_fsm (
    input logic clk,
    input logic rst,
    input logic en,
    output logic [7:0] data_out
);

  logic [7:0] out;
  // Define our states
  typedef enum {
    S0,
    S1,
    S2,
    S3,
    S4,
    S5,
    S6,
    S7,
    S8
  } my_state;
  my_state current_state, next_state;  // instantiane two state objects

  // state registers
  always_ff @(posedge clk, posedge rst) begin
    if (rst) current_state <= S0;  // RST back to state 0
    if (en) current_state <= next_state;  // if enable pressed, advance state
  end
  //next state logic
  always_comb
    case (current_state)
      S0: begin
        next_state = S1;
        out = 8'b0;
      end
      S1: begin
        next_state = S2;
        out = 8'b1;
      end
      S2: begin
        next_state = S3;
        out = 8'b11;
      end
      S3: begin
        next_state = S4;
        out = 8'b111;
      end
      S4: begin
        next_state = S5;
        out = 8'b1111;
      end
      S5: begin
        next_state = S6;
        out = 8'b11111;
      end
      S6: begin
        next_state = S7;
        out = 8'b111111;
      end
      S7: begin
        next_state = S8;
        out = 8'b1111111;
      end
      S8: begin
        next_state = S0;
        out = 8'b11111111;
      end
      default: begin
        next_state = S0;
        out = 8'b11111111;
      end  // in any other scenario 'reset' to S0
    endcase

  // output logic
  assign data_out = out;
endmodule

task4/clktick.sv
module clktick #(
    parameter WIDTH = 5
) (
    // interface signals
    input  logic             clk,  // clock 
    input  logic             rst,  // reset
    input  logic             en,   // enable signal
    input  logic [WIDTH-1:0] N,    // clock divided by N+1
    output logic             tick  // tick output
);

  logic [WIDTH-1:0] count;

  always_ff @(posedge clk)
    if (rst) begin  // Reset down-counter that counts from N to 0 back to N
      tick  <= 1'b0;  // Set tick signal low
      count <= N;
    end else if (en) begin
      if (count == 0) begin  // once down counter reaches zero..
        tick  <= 1'b1;  //.. 'tick' by asserting high to initiate pulse
        count <= N;  // reset its counter back to N
      end else begin
        tick  <= 1'b0;  // if still counting from N to 0 set tick low
        count <= count - 1'b1;  // count down by one
      end
    end
endmodule

task3/f1_seq.sv
module f1_seq (
    input logic [15:0] N_scale,
    input logic en,
    input logic rst,
    input logic clk,
    output logic [7:0] data_out
);

  logic tick;

  clktick my_clktick (
      .N(N_scale),
      .en(en),
      .rst(rst),
      .clk(clk),
      .tick(tick)
  );

  f1_fsm my_f1_fsm (
      .rst(rst),
      .en(tick),
      .clk(clk),
      .data_out(data_out)
  );

endmodule

task3/f1_seq.vcd
$version Generated by VerilatedVcd $end
$date Fri Nov  4 19:46:30 2022 $end
$timescale 1ps $end

 $scope module TOP $end
  $var wire 16 & N_scale [15:0] $end
  $var wire  1 ) clk $end
  $var wire  8 * data_out [7:0] $end
  $var wire  1 ' en $end
  $var wire  1 ( rst $end
  $scope module f1_seq $end
   $var wire 16 & N_scale [15:0] $end
   $var wire  1 ) clk $end
   $var wire  8 * data_out [7:0] $end
   $var wire  1 ' en $end
   $var wire  1 ( rst $end
   $var wire  1 + tick $end
   $scope module my_clktick $end
    $var wire 16 & N [15:0] $end
    $var wire 32 - WIDTH [31:0] $end
    $var wire  1 ) clk $end
    $var wire 16 , count [15:0] $end
    $var wire  1 ' en $end
    $var wire  1 ( rst $end
    $var wire  1 + tick $end
   $upscope $end
   $scope module my_f1_fsm $end
    $var wire  1 ) clk $end
    $var wire 32 $ current_state [31:0] $end
    $var wire  8 * data_out [7:0] $end
    $var wire  1 + en $end
    $var wire 32 % next_state [31:0] $end
    $var wire  8 # out [7:0] $end
    $var wire  1 ( rst $end
   $upscope $end
  $upscope $end
 $upscope $end
$enddefinitions $end


#0
b00000000 #
b00000000000000000000000000000000 $
b00000000000000000000000000000000 %
b0000000000101110 &
1'
1(
1)
b00000000 *
0+
b0000000000000000 ,
b00000000000000000000000000010000 -
#1
b00000000000000000000000000000001 %
0)
#2
1)
b0000000000101110 ,
#3
0)
#4
0(
1)
#5
0)
#6
1)
b0000000000101101 ,
#7
0)
#8
1)
b0000000000101100 ,
#9
0)
#10
1)
b0000000000101011 ,
#11
0)
#12
1)
b0000000000101010 ,
#13
0)
#14
1)
b0000000000101001 ,
#15
0)
#16
1)
b0000000000101000 ,
#17
0)
#18
1)
b0000000000100111 ,
#19
0)
#20
1)
b0000000000100110 ,
#21
0)
#22
1)
b0000000000100101 ,
#23
0)
#24
1)
b0000000000100100 ,
#25
0)
#26
1)
b0000000000100011 ,
#27
0)
#28
1)
b0000000000100010 ,
#29
0)
#30
1)
b0000000000100001 ,
#31
0)
#32
1)
b0000000000100000 ,
#33
0)
#34
1)
b0000000000011111 ,
#35
0)
#36
1)
b0000000000011110 ,
#37
0)
#38
1)
b0000000000011101 ,
#39
0)
#40
1)
b0000000000011100 ,
#41
0)
#42
1)
b0000000000011011 ,
#43
0)
#44
1)
b0000000000011010 ,
#45
0)
#46
1)
b0000000000011001 ,
#47
0)
#48
1)
b0000000000011000 ,
#49
0)
#50
1)
b0000000000010111 ,
#51
0)
#52
1)
b0000000000010110 ,
#53
0)
#54
1)
b0000000000010101 ,
#55
0)
#56
1)
b0000000000010100 ,
#57
0)
#58
1)
b0000000000010011 ,
#59
0)
#60
1)
b0000000000010010 ,
#61
0)
#62
1)
b0000000000010001 ,
#63
0)
#64
1)
b0000000000010000 ,
#65
0)
#66
1)
b0000000000001111 ,
#67
0)
#68
1)
b0000000000001110 ,
#69
0)
#70
1)
b0000000000001101 ,
#71
0)
#72
1)
b0000000000001100 ,
#73
0)
#74
1)
b0000000000001011 ,
#75
0)
#76
1)
b0000000000001010 ,
#77
0)
#78
1)
b0000000000001001 ,
#79
0)
#80
1)
b0000000000001000 ,
#81
0)
#82
1)
b0000000000000111 ,
#83
0)
#84
1)
b0000000000000110 ,
#85
0)
#86
1)
b0000000000000101 ,
#87
0)
#88
1)
b0000000000000100 ,
#89
0)
#90
1)
b0000000000000011 ,
#91
0)
#92
1)
b0000000000000010 ,
#93
0)
#94
1)
b0000000000000001 ,
#95
0)
#96
1)
b0000000000000000 ,
#97
0)
#98
1)
1+
b0000000000101110 ,
#99
0)
#100
b00000001 #
b00000000000000000000000000000001 $
b00000000000000000000000000000010 %
1)
b00000001 *
0+
b0000000000101101 ,
#101
0)
#102
1)
b0000000000101100 ,
#103
0)
#104
1)
b0000000000101011 ,
#105
0)
#106
1)
b0000000000101010 ,
#107
0)
#108
1)
b0000000000101001 ,
#109
0)
#110
1)
b0000000000101000 ,
#111
0)
#112
1)
b0000000000100111 ,
#113
0)
#114
1)
b0000000000100110 ,
#115
0)
#116
1)
b0000000000100101 ,
#117
0)
#118
1)
b0000000000100100 ,
#119
0)
#120
1)
b0000000000100011 ,
#121
0)
#122
1)
b0000000000100010 ,
#123
0)
#124
1)
b0000000000100001 ,
#125
0)
#126
1)
b0000000000100000 ,
#127
0)
#128
1)
b0000000000011111 ,
#129
0)
#130
1)
b0000000000011110 ,
#131
0)
#132
1)
b0000000000011101 ,
#133
0)
#134
1)
b0000000000011100 ,
#135
0)
#136
1)
b0000000000011011 ,
#137
0)
#138
1)
b0000000000011010 ,
#139
0)
#140
1)
b0000000000011001 ,
#141
0)
#142
1)
b0000000000011000 ,
#143
0)
#144
1)
b0000000000010111 ,
#145
0)
#146
1)
b0000000000010110 ,
#147
0)
#148
1)
b0000000000010101 ,
#149
0)
#150
1)
b0000000000010100 ,
#151
0)
#152
1)
b0000000000010011 ,
#153
0)
#154
1)
b0000000000010010 ,
#155
0)
#156
1)
b0000000000010001 ,
#157
0)
#158
1)
b0000000000010000 ,
#159
0)
#160
1)
b0000000000001111 ,
#161
0)
#162
1)
b0000000000001110 ,
#163
0)
#164
1)
b0000000000001101 ,
#165
0)
#166
1)
b0000000000001100 ,
#167
0)
#168
1)
b0000000000001011 ,
#169
0)
#170
1)
b0000000000001010 ,
#171
0)
#172
1)
b0000000000001001 ,
#173
0)
#174
1)
b0000000000001000 ,
#175
0)
#176
1)
b0000000000000111 ,
#177
0)
#178
1)
b0000000000000110 ,
#179
0)
#180
1)
b0000000000000101 ,
#181
0)
#182
1)
b0000000000000100 ,
#183
0)
#184
1)
b0000000000000011 ,
#185
0)
#186
1)
b0000000000000010 ,
#187
0)
#188
1)
b0000000000000001 ,
#189
0)
#190
1)
b0000000000000000 ,
#191
0)
#192
1)
1+
b0000000000101110 ,
#193
0)
#194
b00000011 #
b00000000000000000000000000000010 $
b00000000000000000000000000000011 %
1)
b00000011 *
0+
b0000000000101101 ,
#195
0)
#196
1)
b0000000000101100 ,
#197
0)
#198
1)
b0000000000101011 ,
#199
0)
#200
1)
b0000000000101010 ,
#201
0)
#202
1)
b0000000000101001 ,
#203
0)
#204
1)
b0000000000101000 ,
#205
0)
#206
1)
b0000000000100111 ,
#207
0)
#208
1)
b0000000000100110 ,
#209
0)
#210
1)
b0000000000100101 ,
#211
0)
#212
1)
b0000000000100100 ,
#213
0)
#214
1)
b0000000000100011 ,
#215
0)
#216
1)
b0000000000100010 ,
#217
0)
#218
1)
b0000000000100001 ,
#219
0)
#220
1)
b0000000000100000 ,
#221
0)
#222
1)
b0000000000011111 ,
#223
0)
#224
1)
b0000000000011110 ,
#225
0)
#226
1)
b0000000000011101 ,
#227
0)
#228
1)
b0000000000011100 ,
#229
0)
#230
1)
b0000000000011011 ,
#231
0)
#232
1)
b0000000000011010 ,
#233
0)
#234
1)
b0000000000011001 ,
#235
0)
#236
1)
b0000000000011000 ,
#237
0)
#238
1)
b0000000000010111 ,
#239
0)
#240
1)
b0000000000010110 ,
#241
0)
#242
1)
b0000000000010101 ,
#243
0)
#244
1)
b0000000000010100 ,
#245
0)
#246
1)
b0000000000010011 ,
#247
0)
#248
1)
b0000000000010010 ,
#249
0)
#250
1)
b0000000000010001 ,
#251
0)
#252
1)
b0000000000010000 ,
#253
0)
#254
1)
b0000000000001111 ,
#255
0)
#256
1)
b0000000000001110 ,
#257
0)
#258
1)
b0000000000001101 ,
#259
0)
#260
1)
b0000000000001100 ,
#261
0)
#262
1)
b0000000000001011 ,
#263
0)
#264
1)
b0000000000001010 ,
#265
0)
#266
1)
b0000000000001001 ,
#267
0)
#268
1)
b0000000000001000 ,
#269
0)
#270
1)
b0000000000000111 ,
#271
0)
#272
1)
b0000000000000110 ,
#273
0)
#274
1)
b0000000000000101 ,
#275
0)
#276
1)
b0000000000000100 ,
#277
0)
#278
1)
b0000000000000011 ,
#279
0)
#280
1)
b0000000000000010 ,
#281
0)
#282
1)
b0000000000000001 ,
#283
0)
#284
1)
b0000000000000000 ,
#285
0)
#286
1)
1+
b0000000000101110 ,
#287
0)
#288
b00000111 #
b00000000000000000000000000000011 $
b00000000000000000000000000000100 %
1)
b00000111 *
0+
b0000000000101101 ,
#289
0)
#290
1)
b0000000000101100 ,
#291
0)
#292
1)
b0000000000101011 ,
#293
0)
#294
1)
b0000000000101010 ,
#295
0)
#296
1)
b0000000000101001 ,
#297
0)
#298
1)
b0000000000101000 ,
#299
0)
#300
1)
b0000000000100111 ,
#301
0)
#302
1)
b0000000000100110 ,
#303
0)
#304
1)
b0000000000100101 ,
#305
0)
#306
1)
b0000000000100100 ,
#307
0)
#308
1)
b0000000000100011 ,
#309
0)
#310
1)
b0000000000100010 ,
#311
0)
#312
1)
b0000000000100001 ,
#313
0)
#314
1)
b0000000000100000 ,
#315
0)
#316
1)
b0000000000011111 ,
#317
0)
#318
1)
b0000000000011110 ,
#319
0)
#320
1)
b0000000000011101 ,
#321
0)
#322
1)
b0000000000011100 ,
#323
0)
#324
1)
b0000000000011011 ,
#325
0)
#326
1)
b0000000000011010 ,
#327
0)
#328
1)
b0000000000011001 ,
#329
0)
#330
1)
b0000000000011000 ,
#331
0)
#332
1)
b0000000000010111 ,
#333
0)
#334
1)
b0000000000010110 ,
#335
0)
#336
1)
b0000000000010101 ,
#337
0)
#338
1)
b0000000000010100 ,
#339
0)
#340
1)
b0000000000010011 ,
#341
0)
#342
1)
b0000000000010010 ,
#343
0)
#344
1)
b0000000000010001 ,
#345
0)
#346
1)
b0000000000010000 ,
#347
0)
#348
1)
b0000000000001111 ,
#349
0)
#350
1)
b0000000000001110 ,
#351
0)
#352
1)
b0000000000001101 ,
#353
0)
#354
1)
b0000000000001100 ,
#355
0)
#356
1)
b0000000000001011 ,
#357
0)
#358
1)
b0000000000001010 ,
#359
0)
#360
1)
b0000000000001001 ,
#361
0)
#362
1)
b0000000000001000 ,
#363
0)
#364
1)
b0000000000000111 ,
#365
0)
#366
1)
b0000000000000110 ,
#367
0)
#368
1)
b0000000000000101 ,
#369
0)
#370
1)
b0000000000000100 ,
#371
0)
#372
1)
b0000000000000011 ,
#373
0)
#374
1)
b0000000000000010 ,
#375
0)
#376
1)
b0000000000000001 ,
#377
0)
#378
1)
b0000000000000000 ,
#379
0)
#380
1)
1+
b0000000000101110 ,
#381
0)
#382
b00001111 #
b00000000000000000000000000000100 $
b00000000000000000000000000000101 %
1)
b00001111 *
0+
b0000000000101101 ,
#383
0)
#384
1)
b0000000000101100 ,
#385
0)
#386
1)
b0000000000101011 ,
#387
0)
#388
1)
b0000000000101010 ,
#389
0)
#390
1)
b0000000000101001 ,
#391
0)
#392
1)
b0000000000101000 ,
#393
0)
#394
1)
b0000000000100111 ,
#395
0)
#396
1)
b0000000000100110 ,
#397
0)
#398
1)
b0000000000100101 ,
#399
0)
#400
1)
b0000000000100100 ,
#401
0)
#402
1)
b0000000000100011 ,
#403
0)
#404
1)
b0000000000100010 ,
#405
0)
#406
1)
b0000000000100001 ,
#407
0)
#408
1)
b0000000000100000 ,
#409
0)
#410
1)
b0000000000011111 ,
#411
0)
#412
1)
b0000000000011110 ,
#413
0)
#414
1)
b0000000000011101 ,
#415
0)
#416
1)
b0000000000011100 ,
#417
0)
#418
1)
b0000000000011011 ,
#419
0)
#420
1)
b0000000000011010 ,
#421
0)
#422
1)
b0000000000011001 ,
#423
0)
#424
1)
b0000000000011000 ,
#425
0)
#426
1)
b0000000000010111 ,
#427
0)
#428
1)
b0000000000010110 ,
#429
0)
#430
1)
b0000000000010101 ,
#431
0)
#432
1)
b0000000000010100 ,
#433
0)
#434
1)
b0000000000010011 ,
#435
0)
#436
1)
b0000000000010010 ,
#437
0)
#438
1)
b0000000000010001 ,
#439
0)
#440
1)
b0000000000010000 ,
#441
0)
#442
1)
b0000000000001111 ,
#443
0)
#444
1)
b0000000000001110 ,
#445
0)
#446
1)
b0000000000001101 ,
#447
0)
#448
1)
b0000000000001100 ,
#449
0)
#450
1)
b0000000000001011 ,
#451
0)
#452
1)
b0000000000001010 ,
#453
0)
#454
1)
b0000000000001001 ,
#455
0)
#456
1)
b0000000000001000 ,
#457
0)
#458
1)
b0000000000000111 ,
#459
0)
#460
1)
b0000000000000110 ,
#461
0)
#462
1)
b0000000000000101 ,
#463
0)
#464
1)
b0000000000000100 ,
#465
0)
#466
1)
b0000000000000011 ,
#467
0)
#468
1)
b0000000000000010 ,
#469
0)
#470
1)
b0000000000000001 ,
#471
0)
#472
1)
b0000000000000000 ,
#473
0)
#474
1)
1+
b0000000000101110 ,
#475
0)
#476
b00011111 #
b00000000000000000000000000000101 $
b00000000000000000000000000000110 %
1)
b00011111 *
0+
b0000000000101101 ,
#477
0)
#478
1)
b0000000000101100 ,
#479
0)
#480
1)
b0000000000101011 ,
#481
0)
#482
1)
b0000000000101010 ,
#483
0)
#484
1)
b0000000000101001 ,
#485
0)
#486
1)
b0000000000101000 ,
#487
0)
#488
1)
b0000000000100111 ,
#489
0)
#490
1)
b0000000000100110 ,
#491
0)
#492
1)
b0000000000100101 ,
#493
0)
#494
1)
b0000000000100100 ,
#495
0)
#496
1)
b0000000000100011 ,
#497
0)
#498
1)
b0000000000100010 ,
#499
0)
#500
1)
b0000000000100001 ,
#501
0)
#502
1)
b0000000000100000 ,
#503
0)
#504
1)
b0000000000011111 ,
#505
0)
#506
1)
b0000000000011110 ,
#507
0)
#508
1)
b0000000000011101 ,
#509
0)
#510
1)
b0000000000011100 ,
#511
0)
#512
1)
b0000000000011011 ,
#513
0)
#514
1)
b0000000000011010 ,
#515
0)
#516
1)
b0000000000011001 ,
#517
0)
#518
1)
b0000000000011000 ,
#519
0)
#520
1)
b0000000000010111 ,
#521
0)
#522
1)
b0000000000010110 ,
#523
0)
#524
1)
b0000000000010101 ,
#525
0)
#526
1)
b0000000000010100 ,
#527
0)
#528
1)
b0000000000010011 ,
#529
0)
#530
1)
b0000000000010010 ,
#531
0)
#532
1)
b0000000000010001 ,
#533
0)
#534
1)
b0000000000010000 ,
#535
0)
#536
1)
b0000000000001111 ,
#537
0)
#538
1)
b0000000000001110 ,
#539
0)
#540
1)
b0000000000001101 ,
#541
0)
#542
1)
b0000000000001100 ,
#543
0)
#544
1)
b0000000000001011 ,
#545
0)
#546
1)
b0000000000001010 ,
#547
0)
#548
1)
b0000000000001001 ,
#549
0)
#550
1)
b0000000000001000 ,
#551
0)
#552
1)
b0000000000000111 ,
#553
0)
#554
1)
b0000000000000110 ,
#555
0)
#556
1)
b0000000000000101 ,
#557
0)
#558
1)
b0000000000000100 ,
#559
0)
#560
1)
b0000000000000011 ,
#561
0)
#562
1)
b0000000000000010 ,
#563
0)
#564
1)
b0000000000000001 ,
#565
0)
#566
1)
b0000000000000000 ,
#567
0)
#568
1)
1+
b0000000000101110 ,
#569
0)
#570
b00111111 #
b00000000000000000000000000000110 $
b00000000000000000000000000000111 %
1)
b00111111 *
0+
b0000000000101101 ,
#571
0)
#572
1)
b0000000000101100 ,
#573
0)
#574
1)
b0000000000101011 ,
#575
0)
#576
1)
b0000000000101010 ,
#577
0)
#578
1)
b0000000000101001 ,
#579
0)
#580
1)
b0000000000101000 ,
#581
0)
#582
1)
b0000000000100111 ,
#583
0)
#584
1)
b0000000000100110 ,
#585
0)
#586
1)
b0000000000100101 ,
#587
0)
#588
1)
b0000000000100100 ,
#589
0)
#590
1)
b0000000000100011 ,
#591
0)
#592
1)
b0000000000100010 ,
#593
0)
#594
1)
b0000000000100001 ,
#595
0)
#596
1)
b0000000000100000 ,
#597
0)
#598
1)
b0000000000011111 ,
#599
0)
#600
1)
b0000000000011110 ,
#601
0)
#602
1)
b0000000000011101 ,
#603
0)
#604
1)
b0000000000011100 ,
#605
0)
#606
1)
b0000000000011011 ,
#607
0)
#608
1)
b0000000000011010 ,
#609
0)
#610
1)
b0000000000011001 ,
#611
0)
#612
1)
b0000000000011000 ,
#613
0)
#614
1)
b0000000000010111 ,
#615
0)
#616
1)
b0000000000010110 ,
#617
0)
#618
1)
b0000000000010101 ,
#619
0)
#620
1)
b0000000000010100 ,
#621
0)
#622
1)
b0000000000010011 ,
#623
0)
#624
1)
b0000000000010010 ,
#625
0)
#626
1)
b0000000000010001 ,
#627
0)
#628
1)
b0000000000010000 ,
#629
0)
#630
1)
b0000000000001111 ,
#631
0)
#632
1)
b0000000000001110 ,
#633
0)
#634
1)
b0000000000001101 ,
#635
0)
#636
1)
b0000000000001100 ,
#637
0)
#638
1)
b0000000000001011 ,
#639
0)
#640
1)
b0000000000001010 ,
#641
0)
#642
1)
b0000000000001001 ,
#643
0)
#644
1)
b0000000000001000 ,
#645
0)
#646
1)
b0000000000000111 ,
#647
0)
#648
1)
b0000000000000110 ,
#649
0)
#650
1)
b0000000000000101 ,
#651
0)
#652
1)
b0000000000000100 ,
#653
0)
#654
1)
b0000000000000011 ,
#655
0)
#656
1)
b0000000000000010 ,
#657
0)
#658
1)
b0000000000000001 ,
#659
0)
#660
1)
b0000000000000000 ,
#661
0)
#662
1)
1+
b0000000000101110 ,
#663
0)
#664
b01111111 #
b00000000000000000000000000000111 $
b00000000000000000000000000001000 %
1)
b01111111 *
0+
b0000000000101101 ,
#665
0)
#666
1)
b0000000000101100 ,
#667
0)
#668
1)
b0000000000101011 ,
#669
0)
#670
1)
b0000000000101010 ,
#671
0)
#672
1)
b0000000000101001 ,
#673
0)
#674
1)
b0000000000101000 ,
#675
0)
#676
1)
b0000000000100111 ,
#677
0)
#678
1)
b0000000000100110 ,
#679
0)
#680
1)
b0000000000100101 ,
#681
0)
#682
1)
b0000000000100100 ,
#683
0)
#684
1)
b0000000000100011 ,
#685
0)
#686
1)
b0000000000100010 ,
#687
0)
#688
1)
b0000000000100001 ,
#689
0)
#690
1)
b0000000000100000 ,
#691
0)
#692
1)
b0000000000011111 ,
#693
0)
#694
1)
b0000000000011110 ,
#695
0)
#696
1)
b0000000000011101 ,
#697
0)
#698
1)
b0000000000011100 ,
#699
0)
#700
1)
b0000000000011011 ,
#701
0)
#702
1)
b0000000000011010 ,
#703
0)
#704
1)
b0000000000011001 ,
#705
0)
#706
1)
b0000000000011000 ,
#707
0)
#708
1)
b0000000000010111 ,
#709
0)
#710
1)
b0000000000010110 ,
#711
0)
#712
1)
b0000000000010101 ,
#713
0)
#714
1)
b0000000000010100 ,
#715
0)
#716
1)
b0000000000010011 ,
#717
0)
#718
1)
b0000000000010010 ,
#719
0)
#720
1)
b0000000000010001 ,
#721
0)
#722
1)
b0000000000010000 ,
#723
0)
#724
1)
b0000000000001111 ,
#725
0)
#726
1)
b0000000000001110 ,
#727
0)
#728
1)
b0000000000001101 ,
#729
0)
#730
1)
b0000000000001100 ,
#731
0)
#732
1)
b0000000000001011 ,
#733
0)
#734
1)
b0000000000001010 ,
#735
0)
#736
1)
b0000000000001001 ,
#737
0)
#738
1)
b0000000000001000 ,
#739
0)
#740
1)
b0000000000000111 ,
#741
0)
#742
1)
b0000000000000110 ,
#743
0)
#744
1)
b0000000000000101 ,
#745
0)
#746
1)
b0000000000000100 ,
#747
0)
#748
1)
b0000000000000011 ,
#749
0)
#750
1)
b0000000000000010 ,
#751
0)
#752
1)
b0000000000000001 ,
#753
0)
#754
1)
b0000000000000000 ,
#755
0)
#756
1)
1+
b0000000000101110 ,
#757
0)
#758
b11111111 #
b00000000000000000000000000001000 $
b00000000000000000000000000000000 %
1)
b11111111 *
0+
b0000000000101101 ,
#759
0)
#760
1)
b0000000000101100 ,
#761
0)
#762
1)
b0000000000101011 ,
#763
0)
#764
1)
b0000000000101010 ,
#765
0)
#766
1)
b0000000000101001 ,
#767
0)
#768
1)
b0000000000101000 ,
#769
0)
#770
1)
b0000000000100111 ,
#771
0)
#772
1)
b0000000000100110 ,
#773
0)
#774
1)
b0000000000100101 ,
#775
0)
#776
1)
b0000000000100100 ,
#777
0)
#778
1)
b0000000000100011 ,
#779
0)
#780
1)
b0000000000100010 ,
#781
0)
#782
1)
b0000000000100001 ,
#783
0)
#784
1)
b0000000000100000 ,
#785
0)
#786
1)
b0000000000011111 ,
#787
0)
#788
1)
b0000000000011110 ,
#789
0)
#790
1)
b0000000000011101 ,
#791
0)
#792
1)
b0000000000011100 ,
#793
0)
#794
1)
b0000000000011011 ,
#795
0)
#796
1)
b0000000000011010 ,
#797
0)
#798
1)
b0000000000011001 ,
#799
0)
#800
1)
b0000000000011000 ,
#801
0)
#802
1)
b0000000000010111 ,
#803
0)
#804
1)
b0000000000010110 ,
#805
0)
#806
1)
b0000000000010101 ,
#807
0)
#808
1)
b0000000000010100 ,
#809
0)
#810
1)
b0000000000010011 ,
#811
0)
#812
1)
b0000000000010010 ,
#813
0)
#814
1)
b0000000000010001 ,
#815
0)
#816
1)
b0000000000010000 ,
#817
0)
#818
1)
b0000000000001111 ,
#819
0)
#820
1)
b0000000000001110 ,
#821
0)
#822
1)
b0000000000001101 ,
#823
0)
#824
1)
b0000000000001100 ,
#825
0)
#826
1)
b0000000000001011 ,
#827
0)
#828
1)
b0000000000001010 ,
#829
0)
#830
1)
b0000000000001001 ,
#831
0)
#832
1)
b0000000000001000 ,
#833
0)
#834
1)
b0000000000000111 ,
#835
0)
#836
1)
b0000000000000110 ,
#837
0)
#838
1)
b0000000000000101 ,
#839
0)
#840
1)
b0000000000000100 ,
#841
0)
#842
1)
b0000000000000011 ,
#843
0)
#844
1)
b0000000000000010 ,
#845
0)
#846
1)
b0000000000000001 ,
#847
0)
#848
1)
b0000000000000000 ,
#849
0)
#850
1)
1+
b0000000000101110 ,
#851
0)
#852
b00000000 #
b00000000000000000000000000000000 $
b00000000000000000000000000000001 %
1)
b00000000 *
0+
b0000000000101101 ,
#853
0)
#854
1)
b0000000000101100 ,
#855
0)
#856
1)
b0000000000101011 ,
#857
0)
#858
1)
b0000000000101010 ,
#859
0)
#860
1)
b0000000000101001 ,
#861
0)
#862
1)
b0000000000101000 ,
#863
0)
#864
1)
b0000000000100111 ,
#865
0)
#866
1)
b0000000000100110 ,
#867
0)
#868
1)
b0000000000100101 ,
#869
0)
#870
1)
b0000000000100100 ,
#871
0)
#872
1)
b0000000000100011 ,
#873
0)
#874
1)
b0000000000100010 ,
#875
0)
#876
1)
b0000000000100001 ,
#877
0)
#878
1)
b0000000000100000 ,
#879
0)
#880
1)
b0000000000011111 ,
#881
0)
#882
1)
b0000000000011110 ,
#883
0)
#884
1)
b0000000000011101 ,
#885
0)
#886
1)
b0000000000011100 ,
#887
0)
#888
1)
b0000000000011011 ,
#889
0)
#890
1)
b0000000000011010 ,
#891
0)
#892
1)
b0000000000011001 ,
#893
0)
#894
1)
b0000000000011000 ,
#895
0)
#896
1)
b0000000000010111 ,
#897
0)
#898
1)
b0000000000010110 ,
#899
0)
#900
1)
b0000000000010101 ,
#901
0)
#902
1)
b0000000000010100 ,
#903
0)
#904
1)
b0000000000010011 ,
#905
0)
#906
1)
b0000000000010010 ,
#907
0)
#908
1)
b0000000000010001 ,
#909
0)
#910
1)
b0000000000010000 ,
#911
0)
#912
1)
b0000000000001111 ,
#913
0)
#914
1)
b0000000000001110 ,
#915
0)
#916
1)
b0000000000001101 ,
#917
0)
#918
1)
b0000000000001100 ,
#919
0)
#920
1)
b0000000000001011 ,
#921
0)
#922
1)
b0000000000001010 ,
#923
0)
#924
1)
b0000000000001001 ,
#925
0)
#926
1)
b0000000000001000 ,
#927
0)
#928
1)
b0000000000000111 ,
#929
0)
#930
1)
b0000000000000110 ,
#931
0)
#932
1)
b0000000000000101 ,
#933
0)
#934
1)
b0000000000000100 ,
#935
0)
#936
1)
b0000000000000011 ,
#937
0)
#938
1)
b0000000000000010 ,
#939
0)
#940
1)
b0000000000000001 ,
#941
0)
#942
1)
b0000000000000000 ,
#943
0)
#944
1)
1+
b0000000000101110 ,
#945
0)
#946
b00000001 #
b00000000000000000000000000000001 $
b00000000000000000000000000000010 %
1)
b00000001 *
0+
b0000000000101101 ,
#947
0)
#948
1)
b0000000000101100 ,
#949
0)
#950
1)
b0000000000101011 ,
#951
0)
#952
1)
b0000000000101010 ,
#953
0)
#954
1)
b0000000000101001 ,
#955
0)
#956
1)
b0000000000101000 ,
#957
0)
#958
1)
b0000000000100111 ,
#959
0)
#960
1)
b0000000000100110 ,
#961
0)
#962
1)
b0000000000100101 ,
#963
0)
#964
1)
b0000000000100100 ,
#965
0)
#966
1)
b0000000000100011 ,
#967
0)
#968
1)
b0000000000100010 ,
#969
0)
#970
1)
b0000000000100001 ,
#971
0)
#972
1)
b0000000000100000 ,
#973
0)
#974
1)
b0000000000011111 ,
#975
0)
#976
1)
b0000000000011110 ,
#977
0)
#978
1)
b0000000000011101 ,
#979
0)
#980
1)
b0000000000011100 ,
#981
0)
#982
1)
b0000000000011011 ,
#983
0)
#984
1)
b0000000000011010 ,
#985
0)
#986
1)
b0000000000011001 ,
#987
0)
#988
1)
b0000000000011000 ,
#989
0)
#990
1)
b0000000000010111 ,
#991
0)
#992
1)
b0000000000010110 ,
#993
0)
#994
1)
b0000000000010101 ,
#995
0)
#996
1)
b0000000000010100 ,
#997
0)
#998
1)
b0000000000010011 ,
#999
0)
#1000
1)
b0000000000010010 ,
#1001
0)
#1002
1)
b0000000000010001 ,
#1003
0)
#1004
1)
b0000000000010000 ,
#1005
0)
#1006
1)
b0000000000001111 ,
#1007
0)
#1008
1)
b0000000000001110 ,
#1009
0)
#1010
1)
b0000000000001101 ,
#1011
0)
#1012
1)
b0000000000001100 ,
#1013
0)
#1014
1)
b0000000000001011 ,
#1015
0)
#1016
1)
b0000000000001010 ,
#1017
0)
#1018
1)
b0000000000001001 ,
#1019
0)
#1020
1)
b0000000000001000 ,
#1021
0)
#1022
1)
b0000000000000111 ,
#1023
0)
#1024
1)
b0000000000000110 ,
#1025
0)
#1026
1)
b0000000000000101 ,
#1027
0)
#1028
1)
b0000000000000100 ,
#1029
0)
#1030
1)
b0000000000000011 ,
#1031
0)
#1032
1)
b0000000000000010 ,
#1033
0)
#1034
1)
b0000000000000001 ,
#1035
0)
#1036
1)
b0000000000000000 ,
#1037
0)
#1038
1)
1+
b0000000000101110 ,
#1039
0)
#1040
b00000011 #
b00000000000000000000000000000010 $
b00000000000000000000000000000011 %
1)
b00000011 *
0+
b0000000000101101 ,
#1041
0)
#1042
1)
b0000000000101100 ,
#1043
0)
#1044
1)
b0000000000101011 ,
#1045
0)
#1046
1)
b0000000000101010 ,
#1047
0)
#1048
1)
b0000000000101001 ,
#1049
0)
#1050
1)
b0000000000101000 ,
#1051
0)
#1052
1)
b0000000000100111 ,
#1053
0)
#1054
1)
b0000000000100110 ,
#1055
0)
#1056
1)
b0000000000100101 ,
#1057
0)
#1058
1)
b0000000000100100 ,
#1059
0)
#1060
1)
b0000000000100011 ,
#1061
0)
#1062
1)
b0000000000100010 ,
#1063
0)
#1064
1)
b0000000000100001 ,
#1065
0)
#1066
1)
b0000000000100000 ,
#1067
0)
#1068
1)
b0000000000011111 ,
#1069
0)
#1070
1)
b0000000000011110 ,
#1071
0)
#1072
1)
b0000000000011101 ,
#1073
0)
#1074
1)
b0000000000011100 ,
#1075
0)
#1076
1)
b0000000000011011 ,
#1077
0)
#1078
1)
b0000000000011010 ,
#1079
0)
#1080
1)
b0000000000011001 ,
#1081
0)
#1082
1)
b0000000000011000 ,
#1083
0)
#1084
1)
b0000000000010111 ,
#1085
0)
#1086
1)
b0000000000010110 ,
#1087
0)
