task4/f1_fsm.sv
module f1_fsm (
    input  logic       clk,
    input  logic       rst,
    input  logic       en,
    input  logic       trigger,
    output logic [7:0] data_out,
    output logic       cmd_seq,
    output logic       cmd_delay
);

  logic [7:0] out;
  // Define our states
  typedef enum {
    IDLE,
    S0,
    S1,
    S2,
    S3,
    S4,
    S5,
    S6,
    S7,
    S8
  } my_state;
  my_state current_state, next_state;  // instantiane two state objects

  // state registers
  always_ff @(posedge clk, posedge trigger) begin
    if (rst) current_state <= S0;  // RST back to state 0
    if (en) current_state <= next_state;  // if enable on, advance state
    if (trigger) current_state <= S1;  // if triggered, advance to S0
  end
  //next state logic
  always_comb
    case (current_state)
      S0: begin
        next_state = S1;
        out = 8'b0;
        cmd_delay = 1'b0;
      end
      S1: begin
        next_state = S2;
        out = 8'b1;
        cmd_seq = 1'b1;
      end
      S2: begin
        next_state = S3;
        out = 8'b11;
      end
      S3: begin
        next_state = S4;
        out = 8'b111;
      end
      S4: begin
        next_state = S5;
        out = 8'b1111;
      end
      S5: begin
        next_state = S6;
        out = 8'b11111;
      end
      S6: begin
        next_state = S7;
        out = 8'b111111;
      end
      S7: begin
        next_state = S8;
        out = 8'b1111111;
      end
      S8: begin
        next_state = S0;
        out = 8'b11111111;
        cmd_seq = 1'b0;
        cmd_delay = 1'b1;
      end
      default: begin
        next_state = S0;
      end  // in any other scenario 'reset' to S0
    endcase

  // output logic
  assign data_out = out;
endmodule

task4/mux2.sv
module mux2 (
    input  logic d0,
    d1,
    input  logic s,
    output logic y
);

  assign y = s ? d1 : d0;

endmodule

task4/delay.sv
module delay #(
    parameter WIDTH = 10  // no of bits in delay counter
) (
    input  logic             clk,      // clock signal
    input  logic             rst,      // reset signal
    input  logic             trigger,  // trigger input signal
    input  logic [WIDTH-1:0] n,        // no of clock cycle delay
    output logic             time_out  // output pulse signal
);
  // Declare counter
  logic [WIDTH-1:0] count = {WIDTH{1'b0}};  // internal counter

  // Define our states
  typedef enum {
    IDLE,
    COUNTING,
    TIME_OUT,
    WAIT_LOW
  } my_state;
  my_state current_state, next_state;

  // counter
  always_ff @(posedge clk)
    if (rst | trigger | count == {WIDTH{1'b0}}) count <= n - 1'b1;
    else count <= count - 1'b1;

  // state transition
  always_ff @(posedge clk)
    if (rst) current_state <= IDLE;
    else current_state <= next_state;

  // next state logic
  always_comb
    case (current_state)
      IDLE:     if (trigger == 1'b1) next_state = COUNTING;
 else next_state = current_state;
      COUNTING: if (count == {WIDTH{1'b0}}) next_state = TIME_OUT;
 else next_state = current_state;
      TIME_OUT: if (trigger == 1'b1) next_state = WAIT_LOW;
 else next_state = IDLE;
      WAIT_LOW: if (trigger == 1'b0) next_state = IDLE;
 else next_state = current_state;
      default:  next_state = IDLE;
    endcase

  // output logic
  always_comb
    case (current_state)
      IDLE:     time_out = 1'b0;
      COUNTING: time_out = 1'b0;
      TIME_OUT: time_out = 1'b1;
      WAIT_LOW: time_out = 1'b0;
      default:  time_out = 1'b0;
    endcase
endmodule

task4/lfsr7.sv
module lfsr7 (
    input logic clk,
    input logic rst,
    output logic [6:0] data_out
);

  // implementing primitive polynomial order 7. An example providing maximum length before sequence repetition:
  // 1 + x^3 + x^7 
  logic [7:1] sreg;
  always_ff @(posedge clk) begin
    if (rst) sreg <= 7'b1;  // upon RST value resets to this. Can be anything non-zero
    else sreg <= {sreg[6:1], sreg[3] ^  /* XOR */ sreg[7]};
  end


  assign data_out = sreg;

endmodule

task4/clktick.sv
module clktick #(
    parameter WIDTH = 5
) (
    // interface signals
    input  logic             clk,  // clock 
    input  logic             rst,  // reset
    input  logic             en,   // enable signal
    input  logic [WIDTH-1:0] N,    // clock divided by N+1
    output logic             tick  // tick output
);

  logic [WIDTH-1:0] count;

  always_ff @(posedge clk)
    if (rst) begin  // Reset down-counter that counts from N to 0 back to N
      tick  <= 1'b0;  // Set tick signal low
      count <= N;
    end else if (en) begin
      if (count == 0) begin  // once down counter reaches zero..
        tick  <= 1'b1;  //.. 'tick' by asserting high to initiate pulse
        count <= N;  // reset its counter back to N
      end else begin
        tick  <= 1'b0;  // if still counting from N to 0 set tick low
        count <= count - 1'b1;  // count down by one
      end
    end
endmodule

task4/f1_full.sv
module f1_full (
    input logic trigger,  // Whole circuit trigger. E.g. Vbuddy Flag
    input logic clk,
    input logic rst,
    input logic [4:0] N, // Use clktick to scale down internal clock to only produce clock tick every n internal clock cycles  
    output logic [7:0] data_out
);

  logic cmd_seq;
  logic tick;
  logic [6:0] K;
  logic cmd_delay;
  logic mux_out;
  logic time_out;

  clktick my_clktick (
      .clk(clk),
      .rst(rst),
      .en(cmd_seq),
      .N(N),
      .tick(tick)
  );

  lfsr7 my_lfsr (
      .clk(clk),
      .rst(rst),
      .data_out(K)
  );

  delay my_delay (
      .clk(clk),
      .n(K),
      .trigger(cmd_delay),  // delay block is triggered when next state is lights out
      .rst(rst),
      .time_out(time_out)
  );

  mux2 my_mux (
      time_out,
      tick,
      cmd_seq,
      mux_out
  );

  f1_fsm my_f1_fsm (
      .rst(rst),
      .clk(clk),
      .trigger(trigger),
      .en(mux_out),
      .data_out(data_out),
      .cmd_seq(cmd_seq),
      .cmd_delay(cmd_delay)
  );
endmodule

task4/f1_full.vcd
$version Generated by VerilatedVcd $end
$date Sat Nov  5 15:15:51 2022 $end
$timescale 1ps $end

 $scope module TOP $end
  $var wire  5 . N [4:0] $end
  $var wire  1 , clk $end
  $var wire  8 / data_out [7:0] $end
  $var wire  1 - rst $end
  $var wire  1 + trigger $end
  $scope module f1_full $end
   $var wire  7 1 K [6:0] $end
   $var wire  5 . N [4:0] $end
   $var wire  1 , clk $end
   $var wire  1 # cmd_delay $end
   $var wire  1 0 cmd_seq $end
   $var wire  8 / data_out [7:0] $end
   $var wire  1 2 mux_out $end
   $var wire  1 - rst $end
   $var wire  1 ' tick $end
   $var wire  1 ( time_out $end
   $var wire  1 + trigger $end
   $scope module my_clktick $end
    $var wire  5 . N [4:0] $end
    $var wire 32 5 WIDTH [31:0] $end
    $var wire  1 , clk $end
    $var wire  5 ) count [4:0] $end
    $var wire  1 0 en $end
    $var wire  1 - rst $end
    $var wire  1 ' tick $end
   $upscope $end
   $scope module my_delay $end
    $var wire 32 6 WIDTH [31:0] $end
    $var wire  1 , clk $end
    $var wire  7 3 count [6:0] $end
    $var wire 32 * current_state [31:0] $end
    $var wire  7 1 n [6:0] $end
    $var wire 32 4 next_state [31:0] $end
    $var wire  1 - rst $end
    $var wire  1 ( time_out $end
    $var wire  1 # trigger $end
   $upscope $end
   $scope module my_f1_fsm $end
    $var wire  1 , clk $end
    $var wire  1 # cmd_delay $end
    $var wire  1 0 cmd_seq $end
    $var wire 32 % current_state [31:0] $end
    $var wire  8 / data_out [7:0] $end
    $var wire  1 2 en $end
    $var wire 32 & next_state [31:0] $end
    $var wire  8 $ out [7:0] $end
    $var wire  1 - rst $end
    $var wire  1 + trigger $end
   $upscope $end
   $scope module my_lfsr $end
    $var wire  1 , clk $end
    $var wire  7 1 data_out [6:0] $end
    $var wire  1 - rst $end
    $var wire  7 1 sreg [7:1] $end
   $upscope $end
   $scope module my_mux $end
    $var wire  1 ( d0 $end
    $var wire  1 ' d1 $end
    $var wire  1 0 s $end
    $var wire  1 2 y $end
   $upscope $end
  $upscope $end
 $upscope $end
$enddefinitions $end


#0
0#
b00000000 $
b00000000000000000000000000000000 %
b00000000000000000000000000000000 &
0'
0(
b00000 )
b00000000000000000000000000000000 *
0+
1,
1-
b10000 .
b00000000 /
00
b0000000 1
02
b0000000 3
b00000000000000000000000000000000 4
b00000000000000000000000000000101 5
b00000000000000000000000000000111 6
#1
b00000000000000000000000000000001 &
0,
#2
b00000000000000000000000000000001 %
b00000000000000000000000000000010 &
b10000 )
1,
b0000001 1
b1111111 3
#3
0,
#4
1,
0-
b0000000 3
#5
0,
#6
1,
b0000010 1
#7
0,
#8
1,
b0000100 1
b0000001 3
#9
0,
#10
1,
b0001001 1
b0000000 3
#11
0,
#12
1,
b0010010 1
b0001000 3
#13
0,
#14
1,
b0100100 1
b0000111 3
#15
0,
#16
1,
b1001001 1
b0000110 3
#17
0,
#18
1,
b0010011 1
b0000101 3
#19
0,
#20
1,
b0100110 1
b0000100 3
#21
0,
#22
1,
b1001101 1
b0000011 3
#23
0,
#24
1,
b0011010 1
b0000010 3
#25
0,
#26
1,
b0110100 1
b0000001 3
#27
0,
#28
1,
b1101001 1
b0000000 3
#29
0,
#30
1,
b1010011 1
b1101000 3
#31
0,
#32
1,
b0100111 1
b1100111 3
#33
0,
#34
1,
b1001111 1
b1100110 3
#35
0,
#36
1,
b0011110 1
b1100101 3
#37
0,
#38
1,
b0111101 1
b1100100 3
#39
0,
#40
1,
b1111011 1
b1100011 3
#41
0,
#42
1,
b1110111 1
b1100010 3
#43
0,
#44
1,
b1101110 1
b1100001 3
#45
0,
#46
1,
b1011100 1
b1100000 3
#47
0,
#48
1+
1,
b0111000 1
b1011111 3
#49
b00000001 $
b00000000000000000000000000000010 %
b00000000000000000000000000000011 &
0,
b00000001 /
10
#50
b01111 )
0+
1,
b1110000 1
b1011110 3
#51
0,
#52
b01110 )
1,
b1100001 1
b1011101 3
#53
0,
#54
b01101 )
1,
b1000011 1
b1011100 3
#55
0,
#56
b01100 )
1,
b0000111 1
b1011011 3
#57
0,
#58
b01011 )
1,
b0001111 1
b1011010 3
#59
0,
#60
b01010 )
1,
b0011111 1
b1011001 3
#61
0,
#62
b01001 )
1,
b0111111 1
b1011000 3
#63
0,
#64
b01000 )
1,
b1111111 1
b1010111 3
#65
0,
#66
b00111 )
1,
b1111110 1
b1010110 3
#67
0,
#68
b00110 )
1,
b1111100 1
b1010101 3
#69
0,
#70
b00101 )
1,
b1111000 1
b1010100 3
#71
0,
#72
b00100 )
1,
b1110001 1
b1010011 3
#73
0,
#74
b00011 )
1,
b1100011 1
b1010010 3
#75
0,
#76
b00010 )
1,
b1000111 1
b1010001 3
#77
0,
#78
b00001 )
1,
b0001110 1
b1010000 3
#79
0,
#80
b00000 )
1,
b0011101 1
b1001111 3
#81
0,
#82
1'
b10000 )
1,
b0111011 1
12
b1001110 3
#83
0,
#84
b00000011 $
b00000000000000000000000000000011 %
b00000000000000000000000000000100 &
0'
b01111 )
1,
b00000011 /
b1110110 1
02
b1001101 3
#85
0,
#86
b01110 )
1,
b1101100 1
b1001100 3
#87
0,
#88
b01101 )
1,
b1011000 1
b1001011 3
#89
0,
#90
b01100 )
1,
b0110001 1
b1001010 3
#91
0,
#92
b01011 )
1,
b1100010 1
b1001001 3
#93
0,
#94
b01010 )
1,
b1000101 1
b1001000 3
#95
0,
#96
b01001 )
1,
b0001010 1
b1000111 3
#97
0,
#98
b01000 )
1,
b0010100 1
b1000110 3
#99
0,
#100
b00111 )
1,
b0101001 1
b1000101 3
#101
0,
#102
b00110 )
1,
b1010010 1
b1000100 3
#103
0,
#104
b00101 )
1,
b0100101 1
b1000011 3
#105
0,
#106
b00100 )
1,
b1001011 1
b1000010 3
#107
0,
#108
b00011 )
1,
b0010111 1
b1000001 3
#109
0,
#110
b00010 )
1,
b0101111 1
b1000000 3
#111
0,
#112
b00001 )
1,
b1011111 1
b0111111 3
#113
0,
#114
b00000 )
1,
b0111110 1
b0111110 3
#115
0,
#116
1'
b10000 )
1,
b1111101 1
12
b0111101 3
#117
0,
#118
b00000111 $
b00000000000000000000000000000100 %
b00000000000000000000000000000101 &
0'
b01111 )
1,
b00000111 /
b1111010 1
02
b0111100 3
#119
0,
#120
b01110 )
1,
b1110101 1
b0111011 3
#121
0,
#122
b01101 )
1,
b1101010 1
b0111010 3
#123
0,
#124
b01100 )
1,
b1010101 1
b0111001 3
#125
0,
#126
b01011 )
1,
b0101010 1
b0111000 3
#127
0,
#128
b01010 )
1,
b1010100 1
b0110111 3
#129
0,
#130
b01001 )
1,
b0101000 1
b0110110 3
#131
0,
#132
b01000 )
1,
b1010000 1
b0110101 3
#133
0,
#134
b00111 )
1,
b0100001 1
b0110100 3
#135
0,
#136
b00110 )
1+
1,
b1000010 1
b0110011 3
#137
b00000001 $
b00000000000000000000000000000010 %
b00000000000000000000000000000011 &
0,
b00000001 /
#138
b00101 )
0+
1,
b0000101 1
b0110010 3
#139
0,
#140
b00100 )
1,
b0001011 1
b0110001 3
#141
0,
#142
b00011 )
1,
b0010110 1
b0110000 3
#143
0,
#144
b00010 )
1,
b0101101 1
b0101111 3
#145
0,
#146
b00001 )
1,
b1011011 1
b0101110 3
#147
0,
#148
b00000 )
1,
b0110111 1
b0101101 3
#149
0,
#150
1'
b10000 )
1,
b1101111 1
12
b0101100 3
#151
0,
#152
b00000011 $
b00000000000000000000000000000011 %
b00000000000000000000000000000100 &
0'
b01111 )
1,
b00000011 /
b1011110 1
02
b0101011 3
#153
0,
#154
b01110 )
1,
b0111100 1
b0101010 3
#155
0,
#156
b01101 )
1,
b1111001 1
b0101001 3
#157
0,
#158
b01100 )
1,
b1110011 1
b0101000 3
#159
0,
#160
b01011 )
1,
b1100111 1
b0100111 3
#161
0,
#162
b01010 )
1,
b1001110 1
b0100110 3
#163
0,
#164
b01001 )
1,
b0011100 1
b0100101 3
#165
0,
#166
b01000 )
1,
b0111001 1
b0100100 3
#167
0,
#168
b00111 )
1,
b1110010 1
b0100011 3
#169
0,
#170
b00110 )
1,
b1100101 1
b0100010 3
#171
0,
#172
b00101 )
1,
b1001010 1
b0100001 3
#173
0,
#174
b00100 )
1,
b0010101 1
b0100000 3
#175
0,
#176
b00011 )
1,
b0101011 1
b0011111 3
#177
0,
#178
b00010 )
1,
b1010110 1
b0011110 3
#179
0,
#180
b00001 )
1,
b0101100 1
b0011101 3
#181
0,
#182
b00000 )
1,
b1011001 1
b0011100 3
#183
0,
#184
1'
b10000 )
1,
b0110011 1
12
b0011011 3
#185
0,
#186
b00000111 $
b00000000000000000000000000000100 %
b00000000000000000000000000000101 &
0'
b01111 )
1,
b00000111 /
b1100110 1
02
b0011010 3
#187
0,
#188
b01110 )
1,
b1001100 1
b0011001 3
#189
0,
#190
b01101 )
1,
b0011000 1
b0011000 3
#191
0,
#192
b01100 )
1,
b0110000 1
b0010111 3
#193
0,
#194
b01011 )
1,
b1100000 1
b0010110 3
#195
0,
#196
b01010 )
1,
b1000001 1
b0010101 3
#197
0,
#198
b01001 )
1,
b0000011 1
b0010100 3
#199
0,
#200
b01000 )
1,
b0000110 1
b0010011 3
#201
0,
#202
b00111 )
1,
b0001101 1
b0010010 3
#203
0,
#204
b00110 )
1,
b0011011 1
b0010001 3
#205
0,
#206
b00101 )
1,
b0110110 1
b0010000 3
#207
0,
#208
b00100 )
1,
b1101101 1
b0001111 3
#209
0,
#210
b00011 )
1,
b1011010 1
b0001110 3
#211
0,
#212
b00010 )
1,
b0110101 1
b0001101 3
#213
0,
#214
b00001 )
1,
b1101011 1
b0001100 3
#215
0,
#216
b00000 )
1,
b1010111 1
b0001011 3
#217
0,
#218
1'
b10000 )
1,
b0101110 1
12
b0001010 3
#219
0,
#220
b00001111 $
b00000000000000000000000000000101 %
b00000000000000000000000000000110 &
0'
b01111 )
1,
b00001111 /
b1011101 1
02
b0001001 3
#221
0,
#222
b01110 )
1,
b0111010 1
b0001000 3
#223
0,
#224
b01101 )
1,
b1110100 1
b0000111 3
#225
0,
#226
b01100 )
1,
b1101000 1
b0000110 3
#227
0,
#228
b01011 )
1,
b1010001 1
b0000101 3
#229
0,
#230
b01010 )
1,
b0100011 1
b0000100 3
#231
0,
#232
b01001 )
1,
b1000110 1
b0000011 3
#233
0,
#234
b01000 )
1,
b0001100 1
b0000010 3
#235
0,
#236
b00111 )
1,
b0011001 1
b0000001 3
#237
0,
#238
b00110 )
1,
b0110010 1
b0000000 3
#239
0,
#240
b00101 )
1,
b1100100 1
b0110001 3
#241
0,
#242
b00100 )
1,
b1001000 1
b0110000 3
#243
0,
#244
b00011 )
1,
b0010001 1
b0101111 3
#245
0,
#246
b00010 )
1,
b0100010 1
b0101110 3
#247
0,
#248
b00001 )
1,
b1000100 1
b0101101 3
#249
0,
#250
b00000 )
1,
b0001000 1
b0101100 3
#251
0,
#252
1'
b10000 )
1,
b0010000 1
12
b0101011 3
#253
0,
#254
b00011111 $
b00000000000000000000000000000110 %
b00000000000000000000000000000111 &
0'
b01111 )
1,
b00011111 /
b0100000 1
02
b0101010 3
#255
0,
#256
b01110 )
1,
b1000000 1
b0101001 3
#257
0,
#258
b01101 )
1,
b0000001 1
b0101000 3
#259
0,
#260
b01100 )
1,
b0000010 1
b0100111 3
#261
0,
#262
b01011 )
1,
b0000100 1
b0100110 3
#263
0,
#264
b01010 )
1,
b0001001 1
b0100101 3
#265
0,
#266
b01001 )
1,
b0010010 1
b0100100 3
#267
0,
#268
b01000 )
1,
b0100100 1
b0100011 3
#269
0,
#270
b00111 )
1,
b1001001 1
b0100010 3
#271
0,
#272
b00110 )
1,
b0010011 1
b0100001 3
#273
0,
#274
b00101 )
1,
b0100110 1
b0100000 3
#275
0,
#276
b00100 )
1,
b1001101 1
b0011111 3
#277
0,
#278
b00011 )
1,
b0011010 1
b0011110 3
#279
0,
#280
b00010 )
1,
b0110100 1
b0011101 3
#281
0,
#282
b00001 )
1,
b1101001 1
b0011100 3
#283
0,
#284
b00000 )
1,
b1010011 1
b0011011 3
#285
0,
#286
1'
b10000 )
1,
b0100111 1
12
b0011010 3
#287
0,
#288
b00111111 $
b00000000000000000000000000000111 %
b00000000000000000000000000001000 &
0'
b01111 )
1,
b00111111 /
b1001111 1
02
b0011001 3
#289
0,
#290
b01110 )
1,
b0011110 1
b0011000 3
#291
0,
#292
b01101 )
1,
b0111101 1
b0010111 3
#293
0,
#294
b01100 )
1,
b1111011 1
b0010110 3
#295
0,
#296
b01011 )
1,
b1110111 1
b0010101 3
#297
0,
#298
b01010 )
1,
b1101110 1
b0010100 3
#299
0,
#300
b01001 )
1,
b1011100 1
b0010011 3
#301
0,
#302
b01000 )
1,
b0111000 1
b0010010 3
#303
0,
#304
b00111 )
1,
b1110000 1
b0010001 3
#305
0,
#306
b00110 )
1,
b1100001 1
b0010000 3
#307
0,
#308
b00101 )
1,
b1000011 1
b0001111 3
#309
0,
#310
b00100 )
1,
b0000111 1
b0001110 3
#311
0,
#312
b00011 )
1,
b0001111 1
b0001101 3
#313
0,
#314
b00010 )
1,
b0011111 1
b0001100 3
#315
0,
#316
b00001 )
1,
b0111111 1
b0001011 3
#317
0,
#318
b00000 )
1,
b1111111 1
b0001010 3
#319
0,
#320
1'
b10000 )
1,
b1111110 1
12
b0001001 3
#321
0,
#322
b01111111 $
b00000000000000000000000000001000 %
b00000000000000000000000000001001 &
0'
b01111 )
1,
b01111111 /
b1111100 1
02
b0001000 3
#323
0,
#324
b01110 )
1,
b1111000 1
b0000111 3
#325
0,
#326
b01101 )
1,
b1110001 1
b0000110 3
#327
0,
#328
b01100 )
1,
b1100011 1
b0000101 3
#329
0,
#330
b01011 )
1,
b1000111 1
b0000100 3
#331
0,
#332
b01010 )
1,
b0001110 1
b0000011 3
#333
0,
#334
b01001 )
1,
b0011101 1
b0000010 3
#335
0,
#336
b01000 )
1,
b0111011 1
b0000001 3
#337
0,
#338
b00111 )
1,
b1110110 1
b0000000 3
#339
0,
#340
b00110 )
1,
b1101100 1
b1110101 3
#341
0,
#342
b00101 )
1,
b1011000 1
b1110100 3
#343
0,
#344
b00100 )
1,
b0110001 1
b1110011 3
#345
0,
#346
b00011 )
1,
b1100010 1
b1110010 3
#347
0,
#348
b00010 )
1,
b1000101 1
b1110001 3
#349
0,
#350
b00001 )
1,
b0001010 1
b1110000 3
#351
0,
#352
b00000 )
1,
b0010100 1
b1101111 3
#353
0,
#354
1'
b10000 )
1,
b0101001 1
12
b1101110 3
#355
0,
#356
1#
b11111111 $
b00000000000000000000000000001001 %
b00000000000000000000000000000001 &
0'
b01111 )
1,
b11111111 /
00
b1010010 1
02
b1101101 3
b00000000000000000000000000000001 4
#357
0,
#358
b00000000000000000000000000000001 *
1,
b0100101 1
b1010001 3
#359
0,
#360
1,
b1001011 1
b0100100 3
#361
0,
#362
1,
b0010111 1
b1001010 3
#363
0,
#364
1,
b0101111 1
b0010110 3
#365
0,
#366
1,
b1011111 1
b0101110 3
#367
0,
#368
1,
b0111110 1
b1011110 3
#369
0,
#370
1,
b1111101 1
b0111101 3
#371
0,
#372
1,
b1111010 1
b1111100 3
#373
0,
#374
1,
b1110101 1
b1111001 3
#375
0,
#376
1,
b1101010 1
b1110100 3
#377
0,
#378
1,
b1010101 1
b1101001 3
#379
0,
#380
1,
b0101010 1
b1010100 3
#381
0,
#382
1,
b1010100 1
b0101001 3
#383
0,
#384
1,
b0101000 1
b1010011 3
#385
0,
#386
1,
b1010000 1
b0100111 3
#387
0,
#388
1,
b0100001 1
b1001111 3
#389
0,
#390
1,
b1000010 1
b0100000 3
#391
0,
#392
1,
b0000101 1
b1000001 3
#393
0,
#394
1,
b0001011 1
b0000100 3
#395
0,
#396
1,
b0010110 1
b0001010 3
#397
0,
#398
1,
b0101101 1
b0010101 3
#399
0,
#400
1,
b1011011 1
b0101100 3
#401
0,
#402
1,
b0110111 1
b1011010 3
#403
0,
#404
1,
b1101111 1
b0110110 3
#405
0,
#406
1,
b1011110 1
b1101110 3
#407
0,
#408
1,
b0111100 1
b1011101 3
#409
0,
#410
1,
b1111001 1
b0111011 3
#411
0,
#412
1,
b1110011 1
b1111000 3
#413
0,
#414
1,
b1100111 1
b1110010 3
#415
0,
#416
1,
b1001110 1
b1100110 3
#417
0,
#418
1,
b0011100 1
b1001101 3
#419
0,
#420
1,
b0111001 1
b0011011 3
#421
0,
#422
1,
b1110010 1
b0111000 3
#423
0,
#424
1,
b1100101 1
b1110001 3
#425
0,
#426
1,
b1001010 1
b1100100 3
#427
0,
#428
1,
b0010101 1
b1001001 3
#429
0,
#430
1,
b0101011 1
b0010100 3
#431
0,
#432
1,
b1010110 1
b0101010 3
#433
0,
#434
1,
b0101100 1
b1010101 3
#435
0,
#436
1,
b1011001 1
b0101011 3
#437
0,
#438
1,
b0110011 1
b1011000 3
#439
0,
#440
1,
b1100110 1
b0110010 3
#441
0,
#442
1,
b1001100 1
b1100101 3
#443
0,
#444
1,
b0011000 1
b1001011 3
#445
0,
#446
1,
b0110000 1
b0010111 3
#447
0,
#448
1,
b1100000 1
b0101111 3
#449
0,
#450
1,
b1000001 1
b1011111 3
#451
0,
#452
1,
b0000011 1
b1000000 3
#453
0,
#454
1,
b0000110 1
b0000010 3
#455
0,
#456
1,
b0001101 1
b0000101 3
#457
0,
#458
1,
b0011011 1
b0001100 3
#459
0,
#460
1,
b0110110 1
b0011010 3
#461
0,
#462
1,
b1101101 1
b0110101 3
#463
0,
#464
1,
b1011010 1
b1101100 3
#465
0,
#466
1,
b0110101 1
b1011001 3
#467
0,
#468
1,
b1101011 1
b0110100 3
#469
0,
#470
1,
b1010111 1
b1101010 3
#471
0,
#472
1,
b0101110 1
b1010110 3
#473
0,
#474
1,
b1011101 1
b0101101 3
#475
0,
#476
1,
b0111010 1
b1011100 3
#477
0,
#478
1,
b1110100 1
b0111001 3
#479
0,
#480
1,
b1101000 1
b1110011 3
#481
0,
#482
1,
b1010001 1
b1100111 3
#483
0,
#484
1,
b0100011 1
b1010000 3
#485
0,
#486
1,
b1000110 1
b0100010 3
#487
0,
#488
1,
b0001100 1
b1000101 3
#489
0,
#490
1,
b0011001 1
b0001011 3
#491
0,
#492
1,
b0110010 1
b0011000 3
#493
0,
#494
1,
b1100100 1
b0110001 3
#495
0,
#496
1,
b1001000 1
b1100011 3
#497
0,
#498
1,
b0010001 1
b1000111 3
#499
0,
#500
1,
b0100010 1
b0010000 3
#501
0,
#502
1,
b1000100 1
b0100001 3
#503
0,
#504
1,
b0001000 1
b1000011 3
#505
0,
#506
1,
b0010000 1
b0000111 3
#507
0,
#508
1,
b0100000 1
b0001111 3
#509
0,
#510
1,
b1000000 1
b0011111 3
#511
0,
#512
1,
b0000001 1
b0111111 3
#513
0,
#514
1,
b0000010 1
b0000000 3
b00000000000000000000000000000010 4
#515
0,
#516
1(
b00000000000000000000000000000010 *
1,
b0000100 1
12
b0000001 3
b00000000000000000000000000000011 4
#517
0,
#518
0#
b00000000 $
b00000000000000000000000000000001 %
b00000000000000000000000000000010 &
0(
b00000000000000000000000000000011 *
1,
b00000000 /
b0001001 1
02
b0000011 3
b00000000000000000000000000000000 4
#519
0,
#520
b00000000000000000000000000000000 *
1,
b0010010 1
b0000010 3
#521
0,
#522
1,
b0100100 1
b0000001 3
#523
0,
#524
1,
b1001001 1
b0000000 3
#525
0,
#526
1,
b0010011 1
b1001000 3
#527
0,
#528
1,
b0100110 1
b1000111 3
#529
0,
#530
1,
b1001101 1
b1000110 3
#531
0,
#532
1+
1,
b0011010 1
b1000101 3
#533
b00000001 $
b00000000000000000000000000000010 %
b00000000000000000000000000000011 &
0,
b00000001 /
10
#534
b01110 )
0+
1,
b0110100 1
b1000100 3
#535
0,
#536
b01101 )
1,
b1101001 1
b1000011 3
#537
0,
#538
b01100 )
1,
b1010011 1
b1000010 3
#539
0,
#540
b01011 )
1,
b0100111 1
b1000001 3
#541
0,
#542
b01010 )
1,
b1001111 1
b1000000 3
#543
0,
#544
b01001 )
1,
b0011110 1
b0111111 3
#545
0,
#546
b01000 )
1,
b0111101 1
b0111110 3
#547
0,
#548
b00111 )
1,
b1111011 1
b0111101 3
#549
0,
#550
b00110 )
1,
b1110111 1
b0111100 3
#551
0,
#552
b00101 )
1,
b1101110 1
b0111011 3
#553
0,
#554
b00100 )
1,
b1011100 1
b0111010 3
#555
0,
#556
b00011 )
1,
b0111000 1
b0111001 3
#557
0,
#558
b00010 )
1,
b1110000 1
b0111000 3
#559
0,
#560
b00001 )
1,
b1100001 1
b0110111 3
#561
0,
#562
b00000 )
1,
b1000011 1
b0110110 3
#563
0,
#564
1'
b10000 )
1,
b0000111 1
12
b0110101 3
#565
0,
#566
b00000011 $
b00000000000000000000000000000011 %
b00000000000000000000000000000100 &
0'
b01111 )
1,
b00000011 /
b0001111 1
02
b0110100 3
#567
0,
#568
b01110 )
1,
b0011111 1
b0110011 3
#569
0,
#570
b01101 )
1,
b0111111 1
b0110010 3
#571
0,
#572
b01100 )
1,
b1111111 1
b0110001 3
#573
0,
#574
b01011 )
1,
b1111110 1
b0110000 3
#575
0,
#576
b01010 )
1,
b1111100 1
b0101111 3
#577
0,
#578
b01001 )
1,
b1111000 1
b0101110 3
#579
0,
#580
b01000 )
1,
b1110001 1
b0101101 3
#581
0,
#582
b00111 )
1,
b1100011 1
b0101100 3
#583
0,
#584
b00110 )
1,
b1000111 1
b0101011 3
#585
0,
#586
b00101 )
1,
b0001110 1
b0101010 3
#587
0,
#588
b00100 )
1,
b0011101 1
b0101001 3
#589
0,
#590
b00011 )
1,
b0111011 1
b0101000 3
#591
0,
#592
b00010 )
1,
b1110110 1
b0100111 3
#593
0,
#594
b00001 )
1,
b1101100 1
b0100110 3
#595
0,
#596
b00000 )
1,
b1011000 1
b0100101 3
#597
0,
#598
1'
b10000 )
1,
b0110001 1
12
b0100100 3
#599
0,
#600
b00000111 $
b00000000000000000000000000000100 %
b00000000000000000000000000000101 &
0'
b01111 )
1,
b00000111 /
b1100010 1
02
b0100011 3
#601
0,
#602
b01110 )
1,
b1000101 1
b0100010 3
#603
0,
#604
b01101 )
1,
b0001010 1
b0100001 3
#605
0,
#606
b01100 )
1,
b0010100 1
b0100000 3
#607
0,
#608
b01011 )
1,
b0101001 1
b0011111 3
#609
0,
#610
b01010 )
1,
b1010010 1
b0011110 3
#611
0,
#612
b01001 )
1,
b0100101 1
b0011101 3
#613
0,
#614
b01000 )
1,
b1001011 1
b0011100 3
#615
0,
#616
b00111 )
1,
b0010111 1
b0011011 3
#617
0,
#618
b00110 )
1,
b0101111 1
b0011010 3
#619
0,
#620
b00101 )
1,
b1011111 1
b0011001 3
#621
0,
#622
b00100 )
1,
b0111110 1
b0011000 3
#623
0,
#624
b00011 )
1,
b1111101 1
b0010111 3
#625
0,
#626
b00010 )
1,
b1111010 1
b0010110 3
#627
0,
#628
b00001 )
1,
b1110101 1
b0010101 3
#629
0,
#630
b00000 )
1,
b1101010 1
b0010100 3
#631
0,
#632
1'
b10000 )
1,
b1010101 1
12
b0010011 3
#633
0,
#634
b00001111 $
b00000000000000000000000000000101 %
b00000000000000000000000000000110 &
0'
b01111 )
1,
b00001111 /
b0101010 1
02
b0010010 3
#635
0,
#636
b01110 )
1,
b1010100 1
b0010001 3
#637
0,
#638
b01101 )
1,
b0101000 1
b0010000 3
#639
0,
#640
b01100 )
1,
b1010000 1
b0001111 3
#641
0,
#642
b01011 )
1,
b0100001 1
b0001110 3
#643
0,
#644
b01010 )
1,
b1000010 1
b0001101 3
#645
0,
#646
b01001 )
1,
b0000101 1
b0001100 3
#647
0,
#648
b01000 )
1,
b0001011 1
b0001011 3
#649
0,
#650
b00111 )
1,
b0010110 1
b0001010 3
#651
0,
#652
b00110 )
1,
b0101101 1
b0001001 3
#653
0,
#654
b00101 )
1,
b1011011 1
b0001000 3
#655
0,
#656
b00100 )
1,
b0110111 1
b0000111 3
#657
0,
#658
b00011 )
1,
b1101111 1
b0000110 3
#659
0,
#660
b00010 )
1,
b1011110 1
b0000101 3
#661
0,
#662
b00001 )
1,
b0111100 1
b0000100 3
#663
0,
#664
b00000 )
1,
b1111001 1
b0000011 3
#665
0,
#666
1'
b10000 )
1,
b1110011 1
12
b0000010 3
#667
0,
#668
b00011111 $
b00000000000000000000000000000110 %
b00000000000000000000000000000111 &
0'
b01111 )
1,
b00011111 /
b1100111 1
02
b0000001 3
#669
0,
#670
b01110 )
1,
b1001110 1
b0000000 3
#671
0,
